[{"Data shared ( Data that may be shared with other companies or organizations )": [{"Device or other IDs": "Device or other IDs", "Data shared and for what purpose": [{"Device or other IDs": "Analytics"}]}, {"App info and performance": "Crash logs and Diagnostics", "Data shared and for what purpose": [{"Crash logs": "Analytics", "Diagnostics": "Analytics"}]}, {"Personal info": "Name, Email address, User IDs, Address, Phone number, and Other info", "Data shared and for what purpose": [{"Name": "App functionality, Developer communications, Advertising or marketing, Account management", "Email address": "App functionality, Developer communications, Advertising or marketing, Account management", "User IDs": "App functionality, Analytics, Account management", "Address": "App functionality, Analytics, Fraud prevention, security, and compliance, Account management", "Phone number": "App functionality, Fraud prevention, security, and compliance, Account management", "Other info": "App functionality"}]}, {"App activity": "App interactions", "Data shared and for what purpose": [{"App interactions": "Analytics"}]}, {"Financial info": "User payment info", "Data shared and for what purpose": [{"User payment info": "App functionality, Fraud prevention, security, and compliance, Account management"}]}, {"Location": "Precise location", "Data shared and for what purpose": [{"Precise location": "App functionality, Fraud prevention, security, and compliance, Account management"}]}]}, {"Data collected ( Data this app may collect )": [{"Contacts": "Contacts", "Data collected and for what purpose": [{"Contacts \u00b7 Optional": "App functionality"}]}, {"Personal info": "Name, Email address, User IDs, Address, Phone number, and Other info", "Data collected and for what purpose": [{"Name": "App functionality, Developer communications, Advertising or marketing, Account management", "Email address": "App functionality, Developer communications, Advertising or marketing, Fraud prevention, security, and compliance, Account management", "User IDs": "App functionality, Analytics, Fraud prevention, security, and compliance, Account management", "Address": "App functionality, Analytics, Fraud prevention, security, and compliance, Account management", "Phone number": "App functionality, Developer communications, Fraud prevention, security, and compliance, Account management", "Other info \u00b7 Optional": "App functionality, Personalization"}]}, {"App activity": "Other user-generated content", "Data collected and for what purpose": [{"Other user-generated content \u00b7 Optional": "Analytics"}]}, {"Financial info": "User payment info", "Data collected and for what purpose": [{"User payment info \u00b7 Optional": "App functionality, Fraud prevention, security, and compliance, Account management"}]}]}, {"Security practices": [{"Data is encrypted in transit": "Your data is transferred over a secure connection"}, {"You can request that data be deleted": "The developer provides a way for you to request that your data be deleted"}]}]