[
    {
        "Data shared ( Data that may be shared with other companies or organizations )": [
            {
                "Files and docs": "Files and docs",
                "Data shared and for what purpose": [
                    {
                        "Files and docs": "App functionality"
                    }
                ]
            },
            {
                "Audio": "Voice or sound recordings",
                "Data shared and for what purpose": [
                    {
                        "Voice or sound recordings": "App functionality"
                    }
                ]
            },
            {
                "Location": "Approximate location",
                "Data shared and for what purpose": [
                    {
                        "Approximate location": "App functionality, Analytics, Personalization, Account management"
                    }
                ]
            },
            {
                "Personal info": "Name, Email address, and Phone number",
                "Data shared and for what purpose": [
                    {
                        "Name": "App functionality, Analytics, Personalization, Account management",
                        "Email address": "App functionality, Analytics, Personalization, Account management",
                        "Phone number": "App functionality, Analytics, Personalization, Account management"
                    }
                ]
            },
            {
                "Photos and videos": "Photos and Videos",
                "Data shared and for what purpose": [
                    {
                        "Photos": "App functionality",
                        "Videos": "App functionality"
                    }
                ]
            }
        ]
    },
    {
        "Data collected ( Data this app may collect )": [
            {
                "Device or other IDs": "Device or other IDs",
                "Data collected and for what purpose": [
                    {
                        "Device or other IDs": "App functionality, Analytics"
                    }
                ]
            },
            {
                "Files and docs": "Files and docs",
                "Data collected and for what purpose": [
                    {
                        "Files and docs · Optional": "App functionality"
                    }
                ]
            },
            {
                "Audio": "Voice or sound recordings",
                "Data collected and for what purpose": [
                    {
                        "Voice or sound recordings · Optional": "App functionality"
                    }
                ]
            },
            {
                "App activity": "App interactions and In-app search history",
                "Data collected and for what purpose": [
                    {
                        "App interactions": "Analytics",
                        "In-app search history": "App functionality, Analytics"
                    }
                ]
            },
            {
                "Location": "Approximate location",
                "Data collected and for what purpose": [
                    {
                        "Approximate location · Optional": "App functionality, Analytics, Personalization, Account management"
                    }
                ]
            },
            {
                "Personal info": "Name, Email address, User IDs, and Phone number",
                "Data collected and for what purpose": [
                    {
                        "Name · Optional": "App functionality, Analytics, Personalization, Account management",
                        "Email address": "App functionality, Analytics, Developer communications, Advertising or marketing, Fraud prevention, security, and compliance, Personalization, Account management",
                        "User IDs": "App functionality, Analytics, Personalization, Account management",
                        "Phone number · Optional": "App functionality, Analytics, Developer communications, Fraud prevention, security, and compliance, Personalization, Account management"
                    }
                ]
            },
            {
                "Photos and videos": "Photos and Videos",
                "Data collected and for what purpose": [
                    {
                        "Photos · Optional": "App functionality",
                        "Videos · Optional": "App functionality"
                    }
                ]
            }
        ]
    },
    {
        "Security practices": [
            {
                "Data is encrypted in transit": "Your data is transferred over a secure connection"
            },
            {
                "You can request that data be deleted": "The developer provides a way for you to request that your data be deleted"
            }
        ]
    }
]