{
    "data": [
        {
            "id": "1018770380",
            "type": "apps",
            "href": "/v1/catalog/ie/apps/1018770380?l=en-GB",
            "attributes": {
                "privacyDetails": {
                    "managePrivacyChoicesUrl": null,
                    "privacyTypes": []
                }
            },
            "relationships": {
                "genres": {
                    "href": "/v1/catalog/ie/apps/1018770380/genres?l=en-GB",
                    "data": []
                },
                "developer": {
                    "href": "/v1/catalog/ie/apps/1018770380/developer?l=en-GB",
                    "data": [
                        {
                            "id": "961344760",
                            "type": "developers",
                            "href": "/v1/catalog/ie/developers/961344760?l=en-GB"
                        }
                    ]
                }
            },
            "meta": {
                "contentVersion": {
                    "MZ_INDEXER": 1740138870694,
                    "RTCI": 1738956155406
                }
            }
        }
    ]
}