{
    "data": [
        {
            "id": "1078967478",
            "type": "apps",
            "href": "/v1/catalog/ie/apps/1078967478?l=en-GB",
            "attributes": {
                "privacyDetails": {
                    "managePrivacyChoicesUrl": null,
                    "privacyTypes": []
                }
            },
            "relationships": {
                "genres": {
                    "href": "/v1/catalog/ie/apps/1078967478/genres?l=en-GB",
                    "data": []
                },
                "developer": {
                    "href": "/v1/catalog/ie/apps/1078967478/developer?l=en-GB",
                    "data": [
                        {
                            "id": "402016394",
                            "type": "developers",
                            "href": "/v1/catalog/ie/developers/402016394?l=en-GB"
                        }
                    ]
                }
            },
            "meta": {
                "contentVersion": {
                    "RTCI": 1732026766217,
                    "MZ_INDEXER": 1740033182778
                }
            }
        }
    ]
}