{
    "data": [
        {
            "id": "1097454739",
            "type": "apps",
            "href": "/v1/catalog/ie/apps/1097454739?l=en-GB",
            "attributes": {
                "privacyDetails": {
                    "managePrivacyChoicesUrl": null,
                    "privacyTypes": []
                }
            },
            "relationships": {
                "developer": {
                    "href": "/v1/catalog/ie/apps/1097454739/developer?l=en-GB",
                    "data": [
                        {
                            "id": "1087749205",
                            "type": "developers",
                            "href": "/v1/catalog/ie/developers/1087749205?l=en-GB"
                        }
                    ]
                },
                "genres": {
                    "href": "/v1/catalog/ie/apps/1097454739/genres?l=en-GB",
                    "data": []
                }
            },
            "meta": {
                "contentVersion": {
                    "RTCI": 1731367472538,
                    "MZ_INDEXER": 1739980673489
                }
            }
        }
    ]
}