{
    "data": [
        {
            "id": "1103173781",
            "type": "apps",
            "href": "/v1/catalog/ie/apps/1103173781?l=en-GB",
            "attributes": {
                "privacyDetails": {
                    "managePrivacyChoicesUrl": null,
                    "privacyTypes": []
                }
            },
            "relationships": {
                "genres": {
                    "href": "/v1/catalog/ie/apps/1103173781/genres?l=en-GB",
                    "data": []
                },
                "developer": {
                    "href": "/v1/catalog/ie/apps/1103173781/developer?l=en-GB",
                    "data": [
                        {
                            "id": "1125912796",
                            "type": "developers",
                            "href": "/v1/catalog/ie/developers/1125912796?l=en-GB"
                        }
                    ]
                }
            },
            "meta": {
                "contentVersion": {
                    "MZ_INDEXER": 1740025489988,
                    "RTCI": 1731361008151
                }
            }
        }
    ]
}