{
    "data": [
        {
            "id": "1108428397",
            "type": "apps",
            "href": "/v1/catalog/ie/apps/1108428397?l=en-GB",
            "attributes": {
                "privacyDetails": {
                    "managePrivacyChoicesUrl": null,
                    "privacyTypes": []
                }
            },
            "relationships": {
                "developer": {
                    "href": "/v1/catalog/ie/apps/1108428397/developer?l=en-GB",
                    "data": [
                        {
                            "id": "569580933",
                            "type": "developers",
                            "href": "/v1/catalog/ie/developers/569580933?l=en-GB"
                        }
                    ]
                },
                "genres": {
                    "href": "/v1/catalog/ie/apps/1108428397/genres?l=en-GB",
                    "data": []
                }
            },
            "meta": {
                "contentVersion": {
                    "RTCI": 1738963756411,
                    "MZ_INDEXER": 1740019745649
                }
            }
        }
    ]
}