{"data": [{"id": "1127250193", "type": "apps", "href": "/v1/catalog/ie/apps/1127250193?l=en-GB", "attributes": {"privacyDetails": {"managePrivacyChoicesUrl": null, "privacyTypes": [{"privacyType": "Data Linked to You", "identifier": "DATA_LINKED_TO_YOU", "description": "The following data, which may be collected and linked to your identity, may be used for the following purposes:", "dataCategories": [], "purposes": [{"purpose": "Analytics", "identifier": "ANALYTICS", "dataCategories": [{"dataCategory": "Purchases", "identifier": "PURCHASES", "dataTypes": ["Purchase History"]}, {"dataCategory": "Financial Info", "identifier": "FINANCIAL_INFO", "dataTypes": ["Payment Info", "Other Financial Info"]}, {"dataCategory": "Location", "identifier": "LOCATION", "dataTypes": ["Coarse Location"]}, {"dataCategory": "User Content", "identifier": "USER_CONTENT", "dataTypes": ["Emails or Text Messages", "Customer Support"]}, {"dataCategory": "Identifiers", "identifier": "IDENTIFIERS", "dataTypes": ["User ID", "Device ID"]}, {"dataCategory": "Usage Data", "identifier": "USAGE_DATA", "dataTypes": ["Product Interaction"]}, {"dataCategory": "Diagnostics", "identifier": "DIAGNOSTICS", "dataTypes": ["Crash Data", "Other Diagnostic Data"]}]}, {"purpose": "Product Personalisation", "identifier": "PRODUCT_PERSONALIZATION", "dataCategories": [{"dataCategory": "Purchases", "identifier": "PURCHASES", "dataTypes": ["Purchase History"]}, {"dataCategory": "Financial Info", "identifier": "FINANCIAL_INFO", "dataTypes": ["Payment Info", "Other Financial Info"]}, {"dataCategory": "Location", "identifier": "LOCATION", "dataTypes": ["Coarse Location"]}, {"dataCategory": "Identifiers", "identifier": "IDENTIFIERS", "dataTypes": ["User ID", "Device ID"]}, {"dataCategory": "Usage Data", "identifier": "USAGE_DATA", "dataTypes": ["Product Interaction"]}]}, {"purpose": "App Functionality", "identifier": "APP_FUNCTIONALITY", "dataCategories": [{"dataCategory": "Purchases", "identifier": "PURCHASES", "dataTypes": ["Purchase History"]}, {"dataCategory": "Financial Info", "identifier": "FINANCIAL_INFO", "dataTypes": ["Payment Info", "Other Financial Info"]}, {"dataCategory": "Location", "identifier": "LOCATION", "dataTypes": ["Coarse Location"]}, {"dataCategory": "User Content", "identifier": "USER_CONTENT", "dataTypes": ["Emails or Text Messages", "Customer Support"]}, {"dataCategory": "Identifiers", "identifier": "IDENTIFIERS", "dataTypes": ["User ID", "Device ID"]}, {"dataCategory": "Usage Data", "identifier": "USAGE_DATA", "dataTypes": ["Product Interaction"]}, {"dataCategory": "Diagnostics", "identifier": "DIAGNOSTICS", "dataTypes": ["Crash Data", "Other Diagnostic Data"]}]}, {"purpose": "Other Purposes", "identifier": "OTHER_PURPOSES", "dataCategories": [{"dataCategory": "Financial Info", "identifier": "FINANCIAL_INFO", "dataTypes": ["Other Financial Info"]}]}]}, {"privacyType": "Data Not Linked to You", "identifier": "DATA_NOT_LINKED_TO_YOU", "description": "The following data, which may be collected but is not linked to your identity, may be used for the following purposes:", "dataCategories": [], "purposes": [{"purpose": "Analytics", "identifier": "ANALYTICS", "dataCategories": [{"dataCategory": "Usage Data", "identifier": "USAGE_DATA", "dataTypes": ["Other Usage Data"]}, {"dataCategory": "Diagnostics", "identifier": "DIAGNOSTICS", "dataTypes": ["Performance Data"]}]}, {"purpose": "App Functionality", "identifier": "APP_FUNCTIONALITY", "dataCategories": [{"dataCategory": "Diagnostics", "identifier": "DIAGNOSTICS", "dataTypes": ["Performance Data"]}]}]}]}}, "relationships": {"genres": {"href": "/v1/catalog/ie/apps/1127250193/genres?l=en-GB", "data": []}, "developer": {"href": "/v1/catalog/ie/apps/1127250193/developer?l=en-GB", "data": [{"id": "298867250", "type": "developers", "href": "/v1/catalog/ie/developers/298867250?l=en-GB"}]}}, "meta": {"contentVersion": {"MZ_INDEXER": 1739571827334, "RTCI": 1739568779081}}}]}