{
    "data": [
        {
            "id": "1176914042",
            "type": "apps",
            "href": "/v1/catalog/ie/apps/1176914042?l=en-GB",
            "attributes": {
                "privacyDetails": {
                    "managePrivacyChoicesUrl": null,
                    "privacyTypes": []
                }
            },
            "relationships": {
                "genres": {
                    "href": "/v1/catalog/ie/apps/1176914042/genres?l=en-GB",
                    "data": []
                },
                "developer": {
                    "href": "/v1/catalog/ie/apps/1176914042/developer?l=en-GB",
                    "data": [
                        {
                            "id": "1093080522",
                            "type": "developers",
                            "href": "/v1/catalog/ie/developers/1093080522?l=en-GB"
                        }
                    ]
                }
            },
            "meta": {
                "contentVersion": {
                    "RTCI": 1735349774060,
                    "MZ_INDEXER": 1739951240592
                }
            }
        }
    ]
}