{"data": [{"id": "1235121075", "type": "apps", "href": "/v1/catalog/ie/apps/1235121075?l=en-GB", "attributes": {"privacyDetails": {"managePrivacyChoicesUrl": null, "privacyTypes": [{"privacyType": "Data Not Linked to You", "identifier": "DATA_NOT_LINKED_TO_YOU", "description": "The following data, which may be collected but is not linked to your identity, may be used for the following purposes:", "dataCategories": [], "purposes": [{"purpose": "Analytics", "identifier": "ANALYTICS", "dataCategories": [{"dataCategory": "Identifiers", "identifier": "IDENTIFIERS", "dataTypes": ["User ID"]}, {"dataCategory": "Usage Data", "identifier": "USAGE_DATA", "dataTypes": ["Product Interaction"]}]}, {"purpose": "App Functionality", "identifier": "APP_FUNCTIONALITY", "dataCategories": [{"dataCategory": "Identifiers", "identifier": "IDENTIFIERS", "dataTypes": ["User ID"]}, {"dataCategory": "Diagnostics", "identifier": "DIAGNOSTICS", "dataTypes": ["Crash Data"]}]}]}]}}, "relationships": {"developer": {"href": "/v1/catalog/ie/apps/1235121075/developer?l=en-GB", "data": [{"id": "867119102", "type": "developers", "href": "/v1/catalog/ie/developers/867119102?l=en-GB"}]}, "genres": {"href": "/v1/catalog/ie/apps/1235121075/genres?l=en-GB", "data": []}}, "meta": {"contentVersion": {"MZ_INDEXER": 1739542506378, "RTCI": 1731366197862}}}]}