{
    "data": [
        {
            "id": "1290088609",
            "type": "apps",
            "href": "/v1/catalog/ie/apps/1290088609?l=en-GB",
            "attributes": {
                "privacyDetails": {
                    "managePrivacyChoicesUrl": null,
                    "privacyTypes": []
                }
            },
            "relationships": {
                "genres": {
                    "href": "/v1/catalog/ie/apps/1290088609/genres?l=en-GB",
                    "data": []
                },
                "developer": {
                    "href": "/v1/catalog/ie/apps/1290088609/developer?l=en-GB",
                    "data": [
                        {
                            "id": "555947952",
                            "type": "developers",
                            "href": "/v1/catalog/ie/developers/555947952?l=en-GB"
                        }
                    ]
                }
            },
            "meta": {
                "contentVersion": {
                    "MZ_INDEXER": 1739918387748,
                    "RTCI": 1731377575255
                }
            }
        }
    ]
}