{"data": [{"id": "1415220997", "type": "apps", "href": "/v1/catalog/ie/apps/1415220997?l=en-GB", "attributes": {"privacyDetails": {"managePrivacyChoicesUrl": null, "privacyTypes": [{"privacyType": "Data Not Collected", "identifier": "DATA_NOT_COLLECTED", "description": "The developer does not collect any data from this app.", "dataCategories": [], "purposes": []}]}}, "relationships": {"genres": {"href": "/v1/catalog/ie/apps/1415220997/genres?l=en-GB", "data": []}, "developer": {"href": "/v1/catalog/ie/apps/1415220997/developer?l=en-GB", "data": [{"id": "1391336505", "type": "developers", "href": "/v1/catalog/ie/developers/1391336505?l=en-GB"}]}}, "meta": {"contentVersion": {"MZ_INDEXER": 1740017391557, "RTCI": 1738952415465}}}]}