{
    "data": [
        {
            "id": "1460122995",
            "type": "apps",
            "href": "/v1/catalog/ie/apps/1460122995?l=en-GB",
            "attributes": {
                "privacyDetails": {
                    "managePrivacyChoicesUrl": null,
                    "privacyTypes": []
                }
            },
            "relationships": {
                "developer": {
                    "href": "/v1/catalog/ie/apps/1460122995/developer?l=en-GB",
                    "data": [
                        {
                            "id": "1465074655",
                            "type": "developers",
                            "href": "/v1/catalog/ie/developers/1465074655?l=en-GB"
                        }
                    ]
                },
                "genres": {
                    "href": "/v1/catalog/ie/apps/1460122995/genres?l=en-GB",
                    "data": []
                }
            },
            "meta": {
                "contentVersion": {
                    "RTCI": 1738968987583,
                    "MZ_INDEXER": 1739969236641
                }
            }
        }
    ]
}