{
    "data": [
        {
            "id": "1511272695",
            "type": "apps",
            "href": "/v1/catalog/ie/apps/1511272695?l=en-GB",
            "attributes": {
                "privacyDetails": {
                    "managePrivacyChoicesUrl": null,
                    "privacyTypes": []
                }
            },
            "relationships": {
                "developer": {
                    "href": "/v1/catalog/ie/apps/1511272695/developer?l=en-GB",
                    "data": [
                        {
                            "id": "430006113",
                            "type": "developers",
                            "href": "/v1/catalog/ie/developers/430006113?l=en-GB"
                        }
                    ]
                },
                "genres": {
                    "href": "/v1/catalog/ie/apps/1511272695/genres?l=en-GB",
                    "data": []
                }
            },
            "meta": {
                "contentVersion": {
                    "RTCI": 1738952678904,
                    "MZ_INDEXER": 1740064625121
                }
            }
        }
    ]
}