{
    "data": [
        {
            "id": "1528899135",
            "type": "apps",
            "href": "/v1/catalog/ie/apps/1528899135?l=en-GB",
            "attributes": {
                "privacyDetails": {
                    "managePrivacyChoicesUrl": null,
                    "privacyTypes": []
                }
            },
            "relationships": {
                "genres": {
                    "href": "/v1/catalog/ie/apps/1528899135/genres?l=en-GB",
                    "data": []
                },
                "developer": {
                    "href": "/v1/catalog/ie/apps/1528899135/developer?l=en-GB",
                    "data": [
                        {
                            "id": "1741481582",
                            "type": "developers",
                            "href": "/v1/catalog/ie/developers/1741481582?l=en-GB"
                        }
                    ]
                }
            },
            "meta": {
                "contentVersion": {
                    "MZ_INDEXER": 1740061465244,
                    "RTCI": 1738969711684
                }
            }
        }
    ]
}