{"data": [{"id": "1535337134", "type": "apps", "href": "/v1/catalog/ie/apps/1535337134?l=en-GB", "attributes": {"privacyDetails": {"managePrivacyChoicesUrl": null, "privacyTypes": [{"privacyType": "Data Not Collected", "identifier": "DATA_NOT_COLLECTED", "description": "The developer does not collect any data from this app.", "dataCategories": [], "purposes": []}]}}, "relationships": {"genres": {"href": "/v1/catalog/ie/apps/1535337134/genres?l=en-GB", "data": []}, "developer": {"href": "/v1/catalog/ie/apps/1535337134/developer?l=en-GB", "data": [{"id": "1378832816", "type": "developers", "href": "/v1/catalog/ie/developers/1378832816?l=en-GB"}]}}, "meta": {"contentVersion": {"MZ_INDEXER": 1739510130216, "RTCI": 1731354889941}}}]}