{"data": [{"id": "1572170174", "type": "apps", "href": "/v1/catalog/ie/apps/1572170174?l=en-GB", "attributes": {"privacyDetails": {"managePrivacyChoicesUrl": null, "privacyTypes": [{"privacyType": "Data Not Collected", "identifier": "DATA_NOT_COLLECTED", "description": "The developer does not collect any data from this app.", "dataCategories": [], "purposes": []}]}}, "relationships": {"developer": {"href": "/v1/catalog/ie/apps/1572170174/developer?l=en-GB", "data": [{"id": "1530198199", "type": "developers", "href": "/v1/catalog/ie/developers/1530198199?l=en-GB"}]}, "genres": {"href": "/v1/catalog/ie/apps/1572170174/genres?l=en-GB", "data": []}}, "meta": {"contentVersion": {"MZ_INDEXER": 1739524893579, "RTCI": 1738957058577}}}]}