{"data": [{"id": "1600472119", "type": "apps", "href": "/v1/catalog/ie/apps/1600472119?l=en-GB", "attributes": {"privacyDetails": {"managePrivacyChoicesUrl": "https://l3.evidon.com/site/660/134/1?lang=en-us", "privacyTypes": [{"privacyType": "Data Not Linked to You", "identifier": "DATA_NOT_LINKED_TO_YOU", "description": "The following data, which may be collected but is not linked to your identity, may be used for the following purposes:", "dataCategories": [], "purposes": [{"purpose": "Analytics", "identifier": "ANALYTICS", "dataCategories": [{"dataCategory": "Usage Data", "identifier": "USAGE_DATA", "dataTypes": ["Product Interaction"]}]}, {"purpose": "App Functionality", "identifier": "APP_FUNCTIONALITY", "dataCategories": [{"dataCategory": "Diagnostics", "identifier": "DIAGNOSTICS", "dataTypes": ["Crash Data", "Performance Data"]}]}]}]}}, "relationships": {"genres": {"href": "/v1/catalog/ie/apps/1600472119/genres?l=en-GB", "data": []}, "developer": {"href": "/v1/catalog/ie/apps/1600472119/developer?l=en-GB", "data": [{"id": "508074893", "type": "developers", "href": "/v1/catalog/ie/developers/508074893?l=en-GB"}]}}, "meta": {"contentVersion": {"MZ_INDEXER": 1740065045498, "RTCI": 1731377710984}}}]}