{"data": [{"id": "1617677478", "type": "apps", "href": "/v1/catalog/ie/apps/1617677478?l=en-GB", "attributes": {"privacyDetails": {"managePrivacyChoicesUrl": null, "privacyTypes": [{"privacyType": "Data Not Collected", "identifier": "DATA_NOT_COLLECTED", "description": "The developer does not collect any data from this app.", "dataCategories": [], "purposes": []}]}}, "relationships": {"developer": {"href": "/v1/catalog/ie/apps/1617677478/developer?l=en-GB", "data": [{"id": "1271689638", "type": "developers", "href": "/v1/catalog/ie/developers/1271689638?l=en-GB"}]}, "genres": {"href": "/v1/catalog/ie/apps/1617677478/genres?l=en-GB", "data": []}}, "meta": {"contentVersion": {"RTCI": 1731382378674, "MZ_INDEXER": 1739509428507}}}]}