{"data": [{"id": "1634410417", "type": "apps", "href": "/v1/catalog/ie/apps/1634410417?l=en-GB", "attributes": {"privacyDetails": {"managePrivacyChoicesUrl": null, "privacyTypes": [{"privacyType": "Data Not Collected", "identifier": "DATA_NOT_COLLECTED", "description": "The developer does not collect any data from this app.", "dataCategories": [], "purposes": []}]}}, "relationships": {"developer": {"href": "/v1/catalog/ie/apps/1634410417/developer?l=en-GB", "data": [{"id": "567740333", "type": "developers", "href": "/v1/catalog/ie/developers/567740333?l=en-GB"}]}, "genres": {"href": "/v1/catalog/ie/apps/1634410417/genres?l=en-GB", "data": []}}, "meta": {"contentVersion": {"MZ_INDEXER": 1739543102644, "RTCI": 1731360628024}}}]}