{"data": [{"id": "1672600074", "type": "apps", "href": "/v1/catalog/ie/apps/1672600074?l=en-GB", "attributes": {"privacyDetails": {"managePrivacyChoicesUrl": "https://www.privacypolicies.com/Iventiveteck/codesolution", "privacyTypes": [{"privacyType": "Data Not Collected", "identifier": "DATA_NOT_COLLECTED", "description": "The developer does not collect any data from this app.", "dataCategories": [], "purposes": []}]}}, "relationships": {"genres": {"href": "/v1/catalog/ie/apps/1672600074/genres?l=en-GB", "data": []}, "developer": {"href": "/v1/catalog/ie/apps/1672600074/developer?l=en-GB", "data": [{"id": "1596840969", "type": "developers", "href": "/v1/catalog/ie/developers/1596840969?l=en-GB"}]}}, "meta": {"contentVersion": {"RTCI": 1731376633104, "MZ_INDEXER": 1739545221247}}}]}