{
    "data": [
        {
            "id": "370890948",
            "type": "apps",
            "href": "/v1/catalog/ie/apps/370890948?l=en-GB",
            "attributes": {
                "privacyDetails": {
                    "managePrivacyChoicesUrl": null,
                    "privacyTypes": []
                }
            },
            "relationships": {
                "genres": {
                    "href": "/v1/catalog/ie/apps/370890948/genres?l=en-GB",
                    "data": []
                },
                "developer": {
                    "href": "/v1/catalog/ie/apps/370890948/developer?l=en-GB",
                    "data": [
                        {
                            "id": "370890951",
                            "type": "developers",
                            "href": "/v1/catalog/ie/developers/370890951?l=en-GB"
                        }
                    ]
                }
            },
            "meta": {
                "contentVersion": {
                    "MZ_INDEXER": 1739998825121,
                    "RTCI": 1738957864781
                }
            }
        }
    ]
}