{"data": [{"id": "409783342", "type": "apps", "href": "/v1/catalog/ie/apps/409783342?l=en-GB", "attributes": {"privacyDetails": {"managePrivacyChoicesUrl": null, "privacyTypes": [{"privacyType": "Data Not Collected", "identifier": "DATA_NOT_COLLECTED", "description": "The developer does not collect any data from this app.", "dataCategories": [], "purposes": []}]}}, "relationships": {"developer": {"href": "/v1/catalog/ie/apps/409783342/developer?l=en-GB", "data": [{"id": "409783345", "type": "developers", "href": "/v1/catalog/ie/developers/409783345?l=en-GB"}]}, "genres": {"href": "/v1/catalog/ie/apps/409783342/genres?l=en-GB", "data": []}}, "meta": {"contentVersion": {"MZ_INDEXER": 1739524586994, "RTCI": 1738964924015}}}]}