{
    "data": [
        {
            "id": "481150251",
            "type": "apps",
            "href": "/v1/catalog/ie/apps/481150251?l=en-GB",
            "attributes": {
                "privacyDetails": {
                    "managePrivacyChoicesUrl": null,
                    "privacyTypes": []
                }
            },
            "relationships": {
                "genres": {
                    "href": "/v1/catalog/ie/apps/481150251/genres?l=en-GB",
                    "data": []
                },
                "developer": {
                    "href": "/v1/catalog/ie/apps/481150251/developer?l=en-GB",
                    "data": [
                        {
                            "id": "977908934",
                            "type": "developers",
                            "href": "/v1/catalog/ie/developers/977908934?l=en-GB"
                        }
                    ]
                }
            },
            "meta": {
                "contentVersion": {
                    "RTCI": 1731355522627,
                    "MZ_INDEXER": 1741264811954
                }
            }
        }
    ]
}