{
    "data": [
        {
            "id": "508387957",
            "type": "apps",
            "href": "/v1/catalog/ie/apps/508387957?l=en-GB",
            "attributes": {
                "privacyDetails": {
                    "managePrivacyChoicesUrl": null,
                    "privacyTypes": []
                }
            },
            "relationships": {
                "genres": {
                    "href": "/v1/catalog/ie/apps/508387957/genres?l=en-GB",
                    "data": []
                },
                "developer": {
                    "href": "/v1/catalog/ie/apps/508387957/developer?l=en-GB",
                    "data": [
                        {
                            "id": "344479280",
                            "type": "developers",
                            "href": "/v1/catalog/ie/developers/344479280?l=en-GB"
                        }
                    ]
                }
            },
            "meta": {
                "contentVersion": {
                    "RTCI": 1734683716490,
                    "MZ_INDEXER": 1740025393607
                }
            }
        }
    ]
}