{
    "data": [
        {
            "id": "547825550",
            "type": "apps",
            "href": "/v1/catalog/ie/apps/547825550?l=en-GB",
            "attributes": {
                "privacyDetails": {
                    "managePrivacyChoicesUrl": null,
                    "privacyTypes": []
                }
            },
            "relationships": {
                "genres": {
                    "href": "/v1/catalog/ie/apps/547825550/genres?l=en-GB",
                    "data": []
                },
                "developer": {
                    "href": "/v1/catalog/ie/apps/547825550/developer?l=en-GB",
                    "data": [
                        {
                            "id": "295669712",
                            "type": "developers",
                            "href": "/v1/catalog/ie/developers/295669712?l=en-GB"
                        }
                    ]
                }
            },
            "meta": {
                "contentVersion": {
                    "RTCI": 1738952359208,
                    "MZ_INDEXER": 1741307730115
                }
            }
        }
    ]
}