{"data": [{"id": "587618103", "type": "apps", "href": "/v1/catalog/ie/apps/587618103?l=en-GB", "attributes": {"privacyDetails": {"managePrivacyChoicesUrl": null, "privacyTypes": [{"privacyType": "Data Linked to You", "identifier": "DATA_LINKED_TO_YOU", "description": "The following data, which may be collected and linked to your identity, may be used for the following purposes:", "dataCategories": [], "purposes": [{"purpose": "Developer\u2019s Advertising or Marketing", "identifier": "DEVELOPERS_ADVERTISING", "dataCategories": [{"dataCategory": "Purchases", "identifier": "PURCHASES", "dataTypes": ["Purchase History"]}, {"dataCategory": "Contact Info", "identifier": "CONTACT_INFO", "dataTypes": ["Physical Address", "Email Address", "Name", "Phone Number"]}, {"dataCategory": "Search History", "identifier": "SEARCH_HISTORY", "dataTypes": ["Search History"]}, {"dataCategory": "Browsing History", "identifier": "BROWSING_HISTORY", "dataTypes": ["Browsing History"]}, {"dataCategory": "Identifiers", "identifier": "IDENTIFIERS", "dataTypes": ["User ID", "Device ID"]}, {"dataCategory": "Usage Data", "identifier": "USAGE_DATA", "dataTypes": ["Product Interaction"]}, {"dataCategory": "Sensitive Info", "identifier": "SENSITIVE_INFO", "dataTypes": ["Sensitive Info"]}, {"dataCategory": "Other Data", "identifier": "OTHER", "dataTypes": ["Other Data Types"]}]}, {"purpose": "Analytics", "identifier": "ANALYTICS", "dataCategories": [{"dataCategory": "Purchases", "identifier": "PURCHASES", "dataTypes": ["Purchase History"]}, {"dataCategory": "Financial Info", "identifier": "FINANCIAL_INFO", "dataTypes": ["Payment Info"]}, {"dataCategory": "Contact Info", "identifier": "CONTACT_INFO", "dataTypes": ["Email Address", "Name"]}, {"dataCategory": "Search History", "identifier": "SEARCH_HISTORY", "dataTypes": ["Search History"]}, {"dataCategory": "Browsing History", "identifier": "BROWSING_HISTORY", "dataTypes": ["Browsing History"]}, {"dataCategory": "Identifiers", "identifier": "IDENTIFIERS", "dataTypes": ["User ID", "Device ID"]}, {"dataCategory": "Usage Data", "identifier": "USAGE_DATA", "dataTypes": ["Product Interaction"]}, {"dataCategory": "Sensitive Info", "identifier": "SENSITIVE_INFO", "dataTypes": ["Sensitive Info"]}, {"dataCategory": "Diagnostics", "identifier": "DIAGNOSTICS", "dataTypes": ["Crash Data", "Performance Data"]}, {"dataCategory": "Other Data", "identifier": "OTHER", "dataTypes": ["Other Data Types"]}]}, {"purpose": "Product Personalisation", "identifier": "PRODUCT_PERSONALIZATION", "dataCategories": [{"dataCategory": "Purchases", "identifier": "PURCHASES", "dataTypes": ["Purchase History"]}, {"dataCategory": "Financial Info", "identifier": "FINANCIAL_INFO", "dataTypes": ["Payment Info"]}, {"dataCategory": "Contact Info", "identifier": "CONTACT_INFO", "dataTypes": ["Email Address", "Name"]}, {"dataCategory": "Search History", "identifier": "SEARCH_HISTORY", "dataTypes": ["Search History"]}, {"dataCategory": "Browsing History", "identifier": "BROWSING_HISTORY", "dataTypes": ["Browsing History"]}, {"dataCategory": "Identifiers", "identifier": "IDENTIFIERS", "dataTypes": ["User ID", "Device ID"]}, {"dataCategory": "Usage Data", "identifier": "USAGE_DATA", "dataTypes": ["Product Interaction"]}, {"dataCategory": "Sensitive Info", "identifier": "SENSITIVE_INFO", "dataTypes": ["Sensitive Info"]}, {"dataCategory": "Other Data", "identifier": "OTHER", "dataTypes": ["Other Data Types"]}]}, {"purpose": "App Functionality", "identifier": "APP_FUNCTIONALITY", "dataCategories": [{"dataCategory": "Purchases", "identifier": "PURCHASES", "dataTypes": ["Purchase History"]}, {"dataCategory": "Financial Info", "identifier": "FINANCIAL_INFO", "dataTypes": ["Payment Info"]}, {"dataCategory": "Contact Info", "identifier": "CONTACT_INFO", "dataTypes": ["Physical Address", "Email Address", "Name", "Phone Number"]}, {"dataCategory": "Search History", "identifier": "SEARCH_HISTORY", "dataTypes": ["Search History"]}, {"dataCategory": "Browsing History", "identifier": "BROWSING_HISTORY", "dataTypes": ["Browsing History"]}, {"dataCategory": "Identifiers", "identifier": "IDENTIFIERS", "dataTypes": ["User ID", "Device ID"]}, {"dataCategory": "Usage Data", "identifier": "USAGE_DATA", "dataTypes": ["Product Interaction"]}, {"dataCategory": "Sensitive Info", "identifier": "SENSITIVE_INFO", "dataTypes": ["Sensitive Info"]}, {"dataCategory": "Diagnostics", "identifier": "DIAGNOSTICS", "dataTypes": ["Crash Data", "Performance Data"]}, {"dataCategory": "Other Data", "identifier": "OTHER", "dataTypes": ["Other Data Types"]}]}, {"purpose": "Other Purposes", "identifier": "OTHER_PURPOSES", "dataCategories": [{"dataCategory": "Contact Info", "identifier": "CONTACT_INFO", "dataTypes": ["Physical Address", "Phone Number"]}]}]}]}}, "relationships": {"genres": {"href": "/v1/catalog/ie/apps/587618103/genres?l=en-GB", "data": []}, "developer": {"href": "/v1/catalog/ie/apps/587618103/developer?l=en-GB", "data": [{"id": "559861830", "type": "developers", "href": "/v1/catalog/ie/developers/559861830?l=en-GB"}]}}, "meta": {"contentVersion": {"RTCI": 1739482760611, "MZ_INDEXER": 1739516446174}}}]}