{"data": [{"id": "6475014131", "type": "apps", "href": "/v1/catalog/ie/apps/6475014131?l=en-GB", "attributes": {"privacyDetails": {"managePrivacyChoicesUrl": null, "privacyTypes": [{"privacyType": "Data Not Linked to You", "identifier": "DATA_NOT_LINKED_TO_YOU", "description": "The following data, which may be collected but is not linked to your identity, may be used for the following purposes:", "dataCategories": [], "purposes": [{"purpose": "Analytics", "identifier": "ANALYTICS", "dataCategories": [{"dataCategory": "Diagnostics", "identifier": "DIAGNOSTICS", "dataTypes": ["Other Diagnostic Data"]}]}, {"purpose": "App Functionality", "identifier": "APP_FUNCTIONALITY", "dataCategories": [{"dataCategory": "Identifiers", "identifier": "IDENTIFIERS", "dataTypes": ["User ID", "Device ID"]}]}]}]}}, "relationships": {"genres": {"href": "/v1/catalog/ie/apps/6475014131/genres?l=en-GB", "data": []}, "developer": {"href": "/v1/catalog/ie/apps/6475014131/developer?l=en-GB", "data": [{"id": "1723072375", "type": "developers", "href": "/v1/catalog/ie/developers/1723072375?l=en-GB"}]}}, "meta": {"contentVersion": {"RTCI": 1738956057830, "MZ_INDEXER": 1739498035507}}}]}