{"data": [{"id": "665455691", "type": "apps", "href": "/v1/catalog/ie/apps/665455691?l=en-GB", "attributes": {"privacyDetails": {"managePrivacyChoicesUrl": null, "privacyTypes": [{"privacyType": "Data Not Collected", "identifier": "DATA_NOT_COLLECTED", "description": "The developer does not collect any data from this app.", "dataCategories": [], "purposes": []}]}}, "relationships": {"genres": {"href": "/v1/catalog/ie/apps/665455691/genres?l=en-GB", "data": []}, "developer": {"href": "/v1/catalog/ie/apps/665455691/developer?l=en-GB", "data": [{"id": "665455694", "type": "developers", "href": "/v1/catalog/ie/developers/665455694?l=en-GB"}]}}, "meta": {"contentVersion": {"MZ_INDEXER": 1739495716942, "RTCI": 1738964488353}}}]}