{"data": [{"id": "665802768", "type": "apps", "href": "/v1/catalog/ie/apps/665802768?l=en-GB", "attributes": {"privacyDetails": {"managePrivacyChoicesUrl": null, "privacyTypes": [{"privacyType": "Data Not Collected", "identifier": "DATA_NOT_COLLECTED", "description": "The developer does not collect any data from this app.", "dataCategories": [], "purposes": []}]}}, "relationships": {"genres": {"href": "/v1/catalog/ie/apps/665802768/genres?l=en-GB", "data": []}, "developer": {"href": "/v1/catalog/ie/apps/665802768/developer?l=en-GB", "data": [{"id": "438101050", "type": "developers", "href": "/v1/catalog/ie/developers/438101050?l=en-GB"}]}}, "meta": {"contentVersion": {"MZ_INDEXER": 1739549640018, "RTCI": 1708808181273}}}]}