{"data": [{"id": "6738346001", "type": "apps", "href": "/v1/catalog/ie/apps/6738346001?l=en-GB", "attributes": {"privacyDetails": {"managePrivacyChoicesUrl": null, "privacyTypes": [{"privacyType": "Data Not Linked to You", "identifier": "DATA_NOT_LINKED_TO_YOU", "description": "The following data, which may be collected but is not linked to your identity, may be used for the following purposes:", "dataCategories": [], "purposes": [{"purpose": "Analytics", "identifier": "ANALYTICS", "dataCategories": [{"dataCategory": "Identifiers", "identifier": "IDENTIFIERS", "dataTypes": ["Device ID"]}, {"dataCategory": "Usage Data", "identifier": "USAGE_DATA", "dataTypes": ["Product Interaction"]}]}, {"purpose": "App Functionality", "identifier": "APP_FUNCTIONALITY", "dataCategories": [{"dataCategory": "Identifiers", "identifier": "IDENTIFIERS", "dataTypes": ["Device ID"]}, {"dataCategory": "Usage Data", "identifier": "USAGE_DATA", "dataTypes": ["Product Interaction"]}, {"dataCategory": "Diagnostics", "identifier": "DIAGNOSTICS", "dataTypes": ["Crash Data", "Performance Data"]}]}]}]}}, "relationships": {"developer": {"href": "/v1/catalog/ie/apps/6738346001/developer?l=en-GB", "data": [{"id": "1780308225", "type": "developers", "href": "/v1/catalog/ie/developers/1780308225?l=en-GB"}]}, "genres": {"href": "/v1/catalog/ie/apps/6738346001/genres?l=en-GB", "data": []}}, "meta": {"contentVersion": {"RTCI": 1734029383158, "MZ_INDEXER": 1739550436747}}}]}