{"data": [{"id": "6738761113", "type": "apps", "href": "/v1/catalog/ie/apps/6738761113?l=en-GB", "attributes": {"privacyDetails": {"managePrivacyChoicesUrl": null, "privacyTypes": [{"privacyType": "Data Not Collected", "identifier": "DATA_NOT_COLLECTED", "description": "The developer does not collect any data from this app.", "dataCategories": [], "purposes": []}]}}, "relationships": {"genres": {"href": "/v1/catalog/ie/apps/6738761113/genres?l=en-GB", "data": []}, "developer": {"href": "/v1/catalog/ie/apps/6738761113/developer?l=en-GB", "data": [{"id": "1782234228", "type": "developers", "href": "/v1/catalog/ie/developers/1782234228?l=en-GB"}]}}, "meta": {"contentVersion": {"MZ_INDEXER": 1739544267427, "RTCI": 1738960039025}}}]}