{"data": [{"id": "789621960", "type": "apps", "href": "/v1/catalog/ie/apps/789621960?l=en-GB", "attributes": {"privacyDetails": {"managePrivacyChoicesUrl": null, "privacyTypes": [{"privacyType": "Data Not Collected", "identifier": "DATA_NOT_COLLECTED", "description": "The developer does not collect any data from this app.", "dataCategories": [], "purposes": []}]}}, "relationships": {"genres": {"href": "/v1/catalog/ie/apps/789621960/genres?l=en-GB", "data": []}, "developer": {"href": "/v1/catalog/ie/apps/789621960/developer?l=en-GB", "data": [{"id": "623695974", "type": "developers", "href": "/v1/catalog/ie/developers/623695974?l=en-GB"}]}}, "meta": {"contentVersion": {"MZ_INDEXER": 1739550257832, "RTCI": 1738722759850}}}]}