{
    "data": [
        {
            "id": "810134830",
            "type": "apps",
            "href": "/v1/catalog/ie/apps/810134830?l=en-GB",
            "attributes": {
                "privacyDetails": {
                    "managePrivacyChoicesUrl": null,
                    "privacyTypes": []
                }
            },
            "relationships": {
                "developer": {
                    "href": "/v1/catalog/ie/apps/810134830/developer?l=en-GB",
                    "data": [
                        {
                            "id": "943521785",
                            "type": "developers",
                            "href": "/v1/catalog/ie/developers/943521785?l=en-GB"
                        }
                    ]
                },
                "genres": {
                    "href": "/v1/catalog/ie/apps/810134830/genres?l=en-GB",
                    "data": []
                }
            },
            "meta": {
                "contentVersion": {
                    "MZ_INDEXER": 1740047846692,
                    "RTCI": 1738099274215
                }
            }
        }
    ]
}