{
    "data": [
        {
            "id": "863078831",
            "type": "apps",
            "href": "/v1/catalog/ie/apps/863078831?l=en-GB",
            "attributes": {
                "privacyDetails": {
                    "managePrivacyChoicesUrl": null,
                    "privacyTypes": []
                }
            },
            "relationships": {
                "developer": {
                    "href": "/v1/catalog/ie/apps/863078831/developer?l=en-GB",
                    "data": [
                        {
                            "id": "506014841",
                            "type": "developers",
                            "href": "/v1/catalog/ie/developers/506014841?l=en-GB"
                        }
                    ]
                },
                "genres": {
                    "href": "/v1/catalog/ie/apps/863078831/genres?l=en-GB",
                    "data": []
                }
            },
            "meta": {
                "contentVersion": {
                    "MZ_INDEXER": 1740060081417,
                    "RTCI": 1731371405430
                }
            }
        }
    ]
}