{
    "data": [
        {
            "id": "879940145",
            "type": "apps",
            "href": "/v1/catalog/ie/apps/879940145?l=en-GB",
            "attributes": {
                "privacyDetails": {
                    "managePrivacyChoicesUrl": null,
                    "privacyTypes": []
                }
            },
            "relationships": {
                "developer": {
                    "href": "/v1/catalog/ie/apps/879940145/developer?l=en-GB",
                    "data": [
                        {
                            "id": "338430290",
                            "type": "developers",
                            "href": "/v1/catalog/ie/developers/338430290?l=en-GB"
                        }
                    ]
                },
                "genres": {
                    "href": "/v1/catalog/ie/apps/879940145/genres?l=en-GB",
                    "data": []
                }
            },
            "meta": {
                "contentVersion": {
                    "MZ_INDEXER": 1739939550171,
                    "RTCI": 1738956888641
                }
            }
        }
    ]
}