{"data": [{"id": "887580814", "type": "apps", "href": "/v1/catalog/ie/apps/887580814?l=en-GB", "attributes": {"privacyDetails": {"managePrivacyChoicesUrl": null, "privacyTypes": [{"privacyType": "Data Not Collected", "identifier": "DATA_NOT_COLLECTED", "description": "The developer does not collect any data from this app.", "dataCategories": [], "purposes": []}]}}, "relationships": {"genres": {"href": "/v1/catalog/ie/apps/887580814/genres?l=en-GB", "data": []}, "developer": {"href": "/v1/catalog/ie/apps/887580814/developer?l=en-GB", "data": [{"id": "887580817", "type": "developers", "href": "/v1/catalog/ie/developers/887580817?l=en-GB"}]}}, "meta": {"contentVersion": {"MZ_INDEXER": 1740046800064, "RTCI": 1738952419117}}}]}